mlgo/__init__.py
mlgo/corpus/__init__.py
mlgo/corpus/combine_training_corpus.py
mlgo/corpus/combine_training_corpus_lib.py
mlgo/corpus/extract_ir.py
mlgo/corpus/extract_ir_lib.py
mlgo/corpus/make_corpus.py
mlgo/corpus/make_corpus_lib.py
mlgo_utils-19.0.0.dev202407180600.dist-info/METADATA
mlgo_utils-19.0.0.dev202407180600.dist-info/WHEEL
mlgo_utils-19.0.0.dev202407180600.dist-info/entry_points.txt
mlgo_utils-19.0.0.dev202407180600.dist-info/top_level.txt
mlgo_utils-19.0.0.dev202407180600.dist-info/RECORD
