Metadata-Version: 2.1
Name: mlgo-utils
Version: 19.0.0.dev202407180600
Summary: Tooling for ML in LLVM
License: Apache-2.0 WITH LLVM-exception
Classifier: License :: OSI Approved :: Apache Software License
Requires-Python: >=3.8
